bradford_white_connect_client/__init__.py
bradford_white_connect_client/client.py
bradford_white_connect_client/constants.py
bradford_white_connect_client/exceptions.py
bradford_white_connect_client/helper.py
bradford_white_connect_client/types.py
bradford_white_connect_client-0.0.21.dist-info/LICENSE
bradford_white_connect_client-0.0.21.dist-info/METADATA
bradford_white_connect_client-0.0.21.dist-info/WHEEL
bradford_white_connect_client-0.0.21.dist-info/RECORD
