Metadata-Version: 2.3
Name: bradford_white_connect_client
Version: 0.0.21
Summary: A Python3, async-friendly client library for Bradford White Connect
License: MIT
Author: Andy Blyler
Author-email: ablyler@blyler.cc
Requires-Python: >=3.11.0,<4.0
Classifier: License :: OSI Approved :: MIT License
Classifier: Programming Language :: Python
Classifier: Programming Language :: Python :: 3
Classifier: Programming Language :: Python :: 3.11
Classifier: Programming Language :: Python :: 3.12
Classifier: Programming Language :: Python :: 3.13
Classifier: Programming Language :: Python :: 3.10
Classifier: Programming Language :: Python :: 3.9
Classifier: Programming Language :: Python :: Implementation :: CPython
Classifier: Programming Language :: Python :: Implementation :: PyPy
Requires-Dist: aiohttp (>=3.8.0)
Requires-Dist: dataclasses-json (>=0.6.1)
Project-URL: Repository, https://github.com/ablyler/bradford_white_connect_client
